LICENSE
MANIFEST.in
README.rst
setup.py
mturk/__init__.py
otree_tools/__init__.py
otree_tools/constants.py
otree_tools/export.py
otree_tools/forms.py
otree_tools/prepare_export_data.py
otree_tools/timedatewidgets.py
otree_tools/utils.py
otree_tools/views.py
otree_tools/widgets.py
otree_tools.egg-info/PKG-INFO
otree_tools.egg-info/SOURCES.txt
otree_tools.egg-info/dependency_links.txt
otree_tools.egg-info/requires.txt
otree_tools.egg-info/top_level.txt
otree_tools/forms/__init__.py
otree_tools/forms/fields.py
otree_tools/management/__init__.py
otree_tools/models/__init__.py
otree_tools/models/fields.py
otree_tools/models/models.py
otree_tools/otree_extensions/__init__.py
otree_tools/otree_extensions/admin.py
otree_tools/otree_extensions/consumers.py
otree_tools/otree_extensions/routing.py
otree_tools/otree_extensions/urls.py
otree_tools/radiogrid/__init__.py
otree_tools/radiogrid/compat.py
otree_tools/radiogrid/db.py
otree_tools/radiogrid/fields.py
otree_tools/radiogrid/widgets.py
otree_tools/static/css/bootstrap-datetimepicker.css
otree_tools/static/css/datetimepicker.css
otree_tools/static/css/otree_tools_widgets.css
otree_tools/static/css/slider.css
otree_tools/static/jquery-ui/jquery.ui.labeledslider.css
otree_tools/static/jquery-ui/jquery.ui.labeledslider.js
otree_tools/static/js/bootstrap-datetimepicker.js
otree_tools/static/js/slider.js
otree_tools/static/js/locales/bootstrap-datetimepicker.ar.js
otree_tools/static/js/locales/bootstrap-datetimepicker.bg.js
otree_tools/static/js/locales/bootstrap-datetimepicker.ca.js
otree_tools/static/js/locales/bootstrap-datetimepicker.cs.js
otree_tools/static/js/locales/bootstrap-datetimepicker.da.js
otree_tools/static/js/locales/bootstrap-datetimepicker.de.js
otree_tools/static/js/locales/bootstrap-datetimepicker.ee.js
otree_tools/static/js/locales/bootstrap-datetimepicker.el.js
otree_tools/static/js/locales/bootstrap-datetimepicker.es.js
otree_tools/static/js/locales/bootstrap-datetimepicker.fi.js
otree_tools/static/js/locales/bootstrap-datetimepicker.fr.js
otree_tools/static/js/locales/bootstrap-datetimepicker.he.js
otree_tools/static/js/locales/bootstrap-datetimepicker.hr.js
