Metadata-Version: 1.1
Name: otree-tools
Version: 1.1.14
Summary: set of tools facilitating development, exporting and payment management in oTree
Home-page: https://github.com/chapkovski/otree_tools
Author: Philipp Chapkovski
Author-email: chapkovski@gmail.com
License: MIT License
Platform: UNKNOWN
Classifier: Environment :: Web Environment
Classifier: Framework :: Django
Classifier: Intended Audience :: Developers
Classifier: License :: OSI Approved :: MIT License
Classifier: Operating System :: OS Independent
Classifier: Programming Language :: Python
Classifier: Programming Language :: Python :: 3
Classifier: Programming Language :: Python :: 3.4
Classifier: Programming Language :: Python :: 3.5
Classifier: Topic :: Internet :: WWW/HTTP
Classifier: Topic :: Internet :: WWW/HTTP :: Dynamic Content
